mypyopt/__init__.py
mypyopt/decision_variable.py
mypyopt/exceptions.py
mypyopt/input_output.py
mypyopt/objective_evaluation.py
mypyopt/optimizer.py
mypyopt/optimizer_heuristic_search.py
mypyopt/project_structure.py
mypyopt/return_state_enum.py
mypyopt/search_return_type.py
mypyopt/demos/plot_example/__init__.py
mypyopt/demos/plot_example/main.py
mypyopt/demos/pretend_energyplus/__init__.py
mypyopt/demos/pretend_energyplus/calibrate_walltemperatures.py
mypyopt/demos/pretend_energyplus/in_template.json
mypyopt/demos/pretend_energyplus/pretend_energyplus.py
mypyopt/demos/wall_temperature/__init__.py
mypyopt/demos/wall_temperature/calculate_wall_temperature.py
mypyopt/demos/wall_temperature/optimize_resistance.py
my_py_opt-0.3.dist-info/METADATA
my_py_opt-0.3.dist-info/WHEEL
my_py_opt-0.3.dist-info/top_level.txt
my_py_opt-0.3.dist-info/RECORD
