Metadata-Version: 2.1
Name: my-py-opt
Version: 0.3
Summary: Lightweight optimization library
Home-page: https://github.com/Myoldmopar/MyPyOpt
Author: Edwin Lee
License: UnlicensedForNow
Platform: UNKNOWN
